vercel/workers/__init__.py
vercel/workers/aio.py
vercel/workers/asgi.py
vercel/workers/callback.py
vercel/workers/client.py
vercel/workers/exceptions.py
vercel/workers/wsgi.py
vercel/workers/celery/__init__.py
vercel/workers/celery/app.py
vercel/workers/celery/transport.py
vercel/workers/celery/utils.py
vercel/workers/celery/worker.py
vercel/workers/django/__init__.py
vercel/workers/django/app.py
vercel/workers/django/backend.py
vercel/workers/django/worker.py
vercel/workers/dramatiq/__init__.py
vercel/workers/dramatiq/app.py
vercel/workers/dramatiq/broker.py
vercel/workers/dramatiq/worker.py
vercel_workers-0.0.10.dist-info/METADATA
vercel_workers-0.0.10.dist-info/WHEEL
vercel_workers-0.0.10.dist-info/entry_points.txt
vercel_workers-0.0.10.dist-info/top_level.txt
vercel_workers-0.0.10.dist-info/RECORD
