Metadata-Version: 2.4
Name: vercel-workers
Version: 0.0.10
Summary: Python SDK for Vercel Workers
License-Expression: MIT
Requires-Python: >=3.12
Requires-Dist: httpx>=0.27.0
Requires-Dist: pydantic>=2.7.0
Requires-Dist: anyio>=4.0.0
Requires-Dist: python-dotenv
Requires-Dist: vercel>=0.3.7
Provides-Extra: dev
Requires-Dist: ruff>=0.5.0; extra == "dev"
Requires-Dist: pytest>=7.0.0; extra == "dev"
Requires-Dist: pytest-asyncio; extra == "dev"
Requires-Dist: mypy; extra == "dev"
Requires-Dist: build>=1.3.0; extra == "dev"
Requires-Dist: twine>=6.2.0; extra == "dev"
Provides-Extra: celery
Requires-Dist: celery>=5.3.0; extra == "celery"
Provides-Extra: django
Requires-Dist: Django>=6.0.0; extra == "django"
Provides-Extra: dramatiq
Requires-Dist: dramatiq>=1.14.0; extra == "dramatiq"
Provides-Extra: examples
Requires-Dist: fastapi; extra == "examples"
Provides-Extra: all
Requires-Dist: vercel-workers[celery]; extra == "all"
Requires-Dist: vercel-workers[django]; extra == "all"
Requires-Dist: vercel-workers[dramatiq]; extra == "all"
